{"grade_point": [{"grade_id": 8, "grade_point": 999, "count": 234}, {"grade_id": 8, "grade_point": 800, "count": 77}, {"grade_id": 8, "grade_point": 600, "count": 201}, {"grade_id": 8, "grade_point": 400, "count": 358}, {"grade_id": 8, "grade_point": 200, "count": 1004}, {"grade_id": 8, "grade_point": 0, "count": 1607}, {"grade_id": 7, "grade_point": 0, "count": 48}, {"grade_id": 6, "grade_point": 0, "count": 30}, {"grade_id": 5, "grade_point": 0, "count": 15}, {"grade_id": 4, "grade_point": 0, "count": 16}, {"grade_id": 3, "grade_point": 0, "count": 4}, {"grade_id": 2, "grade_point": 0, "count": 2}], "golden_ikura_num": [{"golden_ikura_num": 235, "count": 4}, {"golden_ikura_num": 230, "count": 3}, {"golden_ikura_num": 220, "count": 4}, {"golden_ikura_num": 215, "count": 6}, {"golden_ikura_num": 210, "count": 10}, {"golden_ikura_num": 205, "count": 21}, {"golden_ikura_num": 200, "count": 15}, {"golden_ikura_num": 195, "count": 25}, {"golden_ikura_num": 190, "count": 26}, {"golden_ikura_num": 185, "count": 43}, {"golden_ikura_num": 180, "count": 78}, {"golden_ikura_num": 175, "count": 90}, {"golden_ikura_num": 170, "count": 111}, {"golden_ikura_num": 165, "count": 174}, {"golden_ikura_num": 160, "count": 338}, {"golden_ikura_num": 155, "count": 417}, {"golden_ikura_num": 150, "count": 741}, {"golden_ikura_num": 145, "count": 1061}, {"golden_ikura_num": 140, "count": 1579}, {"golden_ikura_num": 135, "count": 2209}, {"golden_ikura_num": 130, "count": 2995}, {"golden_ikura_num": 125, "count": 3890}, {"golden_ikura_num": 120, "count": 4591}, {"golden_ikura_num": 115, "count": 5318}, {"golden_ikura_num": 110, "count": 5560}, {"golden_ikura_num": 105, "count": 5565}, {"golden_ikura_num": 100, "count": 5257}, {"golden_ikura_num": 95, "count": 4728}, {"golden_ikura_num": 90, "count": 3499}, {"golden_ikura_num": 85, "count": 2491}, {"golden_ikura_num": 80, "count": 1676}, {"golden_ikura_num": 75, "count": 1074}, {"golden_ikura_num": 70, "count": 702}, {"golden_ikura_num": 65, "count": 611}, {"golden_ikura_num": 60, "count": 604}, {"golden_ikura_num": 55, "count": 823}, {"golden_ikura_num": 50, "count": 872}, {"golden_ikura_num": 45, "count": 696}, {"golden_ikura_num": 40, "count": 420}, {"golden_ikura_num": 35, "count": 296}, {"golden_ikura_num": 30, "count": 156}, {"golden_ikura_num": 25, "count": 185}, {"golden_ikura_num": 20, "count": 1156}, {"golden_ikura_num": 15, "count": 732}, {"golden_ikura_num": 10, "count": 279}, {"golden_ikura_num": 5, "count": 174}, {"golden_ikura_num": 0, "count": 96}], "distribution": {"golden_ikura_num_avg": "104.298", "golden_ikura_num_std": "30.379", "ikura_num_avg": "3821.996", "ikura_num_std": "1379.362"}, "status": [{"play_time": "2023-05-23T07:00:00.000Z", "grade_point": "492.368", "max_golden_ikura_num": 141, "avg_golden_ikura_num": "110.632", "is_clear_by_rate": [18, 16, 13, 10], "is_failure_by_rate": [17, 14, 9, 6], "failure_wave": [7, 7, 5], "shifts_worked": 38}, {"play_time": "2023-05-23T06:30:00.000Z", "grade_point": "500.526", "max_golden_ikura_num": 188, "avg_golden_ikura_num": "117.44", "is_clear_by_rate": [159, 129, 112, 70], "is_failure_by_rate": [93, 84, 60, 47], "failure_wave": [30, 36, 34], "shifts_worked": 266}, {"play_time": "2023-05-23T06:00:00.000Z", "grade_point": "511.17", "max_golden_ikura_num": 208, "avg_golden_ikura_num": "118.144", "is_clear_by_rate": [228, 183, 143, 116], "is_failure_by_rate": [153, 138, 97, 70], "failure_wave": [49, 43, 65], "shifts_worked": 393}, {"play_time": "2023-05-23T05:30:00.000Z", "grade_point": "490.734", "max_golden_ikura_num": 192, "avg_golden_ikura_num": "116.668", "is_clear_by_rate": [271, 226, 160, 129], "is_failure_by_rate": [177, 140, 106, 81], "failure_wave": [62, 49, 69], "shifts_worked": 463}, {"play_time": "2023-05-23T05:00:00.000Z", "grade_point": "517.768", "max_golden_ikura_num": 210, "avg_golden_ikura_num": "119.071", "is_clear_by_rate": [276, 225, 167, 134], "is_failure_by_rate": [179, 152, 112, 88], "failure_wave": [42, 57, 84], "shifts_worked": 466}, {"play_time": "2023-05-23T04:30:00.000Z", "grade_point": "515.029", "max_golden_ikura_num": 215, "avg_golden_ikura_num": "117.676", "is_clear_by_rate": [293, 239, 182, 143], "is_failure_by_rate": [200, 173, 128, 104], "failure_wave": [55, 58, 94], "shifts_worked": 513}, {"play_time": "2023-05-23T04:00:00.000Z", "grade_point": "481.768", "max_golden_ikura_num": 182, "avg_golden_ikura_num": "115.668", "is_clear_by_rate": [304, 238, 173, 127], "is_failure_by_rate": [174, 139, 102, 77], "failure_wave": [37, 68, 80], "shifts_worked": 495}, {"play_time": "2023-05-23T03:30:00.000Z", "grade_point": "486.647", "max_golden_ikura_num": 173, "avg_golden_ikura_num": "116.943", "is_clear_by_rate": [305, 247, 192, 126], "is_failure_by_rate": [181, 160, 106, 83], "failure_wave": [43, 68, 80], "shifts_worked": 507}, {"play_time": "2023-05-23T03:00:00.000Z", "grade_point": "469.165", "max_golden_ikura_num": 177, "avg_golden_ikura_num": "116.324", "is_clear_by_rate": [283, 230, 179, 114], "is_failure_by_rate": [170, 142, 96, 68], "failure_wave": [50, 60, 76], "shifts_worked": 473}, {"play_time": "2023-05-23T02:30:00.000Z", "grade_point": "465.134", "max_golden_ikura_num": 188, "avg_golden_ikura_num": "114.759", "is_clear_by_rate": [266, 212, 158, 114], "is_failure_by_rate": [162, 131, 93, 63], "failure_wave": [36, 60, 75], "shifts_worked": 449}, {"play_time": "2023-05-23T02:00:00.000Z", "grade_point": "452.732", "max_golden_ikura_num": 197, "avg_golden_ikura_num": "114.717", "is_clear_by_rate": [243, 181, 142, 102], "is_failure_by_rate": [150, 125, 87, 52], "failure_wave": [38, 36, 85], "shifts_worked": 410}, {"play_time": "2023-05-23T01:30:00.000Z", "grade_point": "452.806", "max_golden_ikura_num": 188, "avg_golden_ikura_num": "115.335", "is_clear_by_rate": [264, 205, 150, 86], "is_failure_by_rate": [196, 146, 122, 69], "failure_wave": [45, 66, 91], "shifts_worked": 474}, {"play_time": "2023-05-23T01:00:00.000Z", "grade_point": "446.398", "max_golden_ikura_num": 184, "avg_golden_ikura_num": "115.018", "is_clear_by_rate": [263, 219, 148, 79], "is_failure_by_rate": [183, 150, 105, 69], "failure_wave": [43, 61, 88], "shifts_worked": 465}, {"play_time": "2023-05-23T00:30:00.000Z", "grade_point": "417.148", "max_golden_ikura_num": 189, "avg_golden_ikura_num": "114.813", "is_clear_by_rate": [260, 198, 136, 81], "is_failure_by_rate": [165, 136, 90, 62], "failure_wave": [37, 67, 72], "shifts_worked": 454}, {"play_time": "2023-05-23T00:00:00.000Z", "grade_point": "454.114", "max_golden_ikura_num": 176, "avg_golden_ikura_num": "114.071", "is_clear_by_rate": [190, 141, 97, 69], "is_failure_by_rate": [142, 129, 94, 64], "failure_wave": [39, 46, 67], "shifts_worked": 350}, {"play_time": "2023-05-22T23:30:00.000Z", "grade_point": "452.391", "max_golden_ikura_num": 151, "avg_golden_ikura_num": "112.186", "is_clear_by_rate": [165, 127, 90, 76], "is_failure_by_rate": [125, 96, 61, 44], "failure_wave": [30, 48, 49], "shifts_worked": 299}, {"play_time": "2023-05-22T23:00:00.000Z", "grade_point": "455.645", "max_golden_ikura_num": 157, "avg_golden_ikura_num": "110.84", "is_clear_by_rate": [139, 101, 77, 56], "is_failure_by_rate": [134, 114, 75, 48], "failure_wave": [39, 35, 61], "shifts_worked": 279}, {"play_time": "2023-05-22T22:30:00.000Z", "grade_point": "476.934", "max_golden_ikura_num": 177, "avg_golden_ikura_num": "112.948", "is_clear_by_rate": [114, 98, 69, 42], "is_failure_by_rate": [96, 81, 51, 35], "failure_wave": [23, 32, 41], "shifts_worked": 212}, {"play_time": "2023-05-22T22:00:00.000Z", "grade_point": "473.226", "max_golden_ikura_num": 177, "avg_golden_ikura_num": "116.67", "is_clear_by_rate": [98, 83, 59, 33], "is_failure_by_rate": [85, 68, 49, 37], "failure_wave": [23, 30, 33], "shifts_worked": 186}, {"play_time": "2023-05-22T21:30:00.000Z", "grade_point": "452.474", "max_golden_ikura_num": 165, "avg_golden_ikura_num": "116.223", "is_clear_by_rate": [103, 78, 64, 45], "is_failure_by_rate": [91, 59, 40, 26], "failure_wave": [18, 30, 43], "shifts_worked": 194}, {"play_time": "2023-05-22T21:00:00.000Z", "grade_point": "472.429", "max_golden_ikura_num": 177, "avg_golden_ikura_num": "116.853", "is_clear_by_rate": [109, 91, 66, 50], "is_failure_by_rate": [98, 72, 53, 38], "failure_wave": [22, 30, 51], "shifts_worked": 212}, {"play_time": "2023-05-22T20:30:00.000Z", "grade_point": "514.07", "max_golden_ikura_num": 163, "avg_golden_ikura_num": "114.734", "is_clear_by_rate": [135, 119, 90, 56], "is_failure_by_rate": [74, 62, 49, 38], "failure_wave": [13, 26, 37], "shifts_worked": 215}, {"play_time": "2023-05-22T20:00:00.000Z", "grade_point": "488.634", "max_golden_ikura_num": 164, "avg_golden_ikura_num": "116.795", "is_clear_by_rate": [132, 116, 90, 47], "is_failure_by_rate": [91, 73, 53, 40], "failure_wave": [28, 27, 40], "shifts_worked": 227}, {"play_time": "2023-05-22T19:30:00.000Z", "grade_point": "485.52", "max_golden_ikura_num": 154, "avg_golden_ikura_num": "115.689", "is_clear_by_rate": [151, 123, 99, 56], "is_failure_by_rate": [128, 98, 76, 51], "failure_wave": [34, 39, 55], "shifts_worked": 279}, {"play_time": "2023-05-22T19:00:00.000Z", "grade_point": "501.899", "max_golden_ikura_num": 160, "avg_golden_ikura_num": "116.209", "is_clear_by_rate": [187, 166, 124, 79], "is_failure_by_rate": [129, 104, 69, 43], "failure_wave": [32, 41, 56], "shifts_worked": 316}, {"play_time": "2023-05-22T18:30:00.000Z", "grade_point": "503.956", "max_golden_ikura_num": 172, "avg_golden_ikura_num": "117.034", "is_clear_by_rate": [201, 175, 126, 74], "is_failure_by_rate": [155, 136, 96, 76], "failure_wave": [37, 55, 64], "shifts_worked": 364}, {"play_time": "2023-05-22T18:00:00.000Z", "grade_point": "467.265", "max_golden_ikura_num": 176, "avg_golden_ikura_num": "116.578", "is_clear_by_rate": [246, 211, 130, 86], "is_failure_by_rate": [172, 150, 107, 73], "failure_wave": [44, 42, 93], "shifts_worked": 437}, {"play_time": "2023-05-22T17:30:00.000Z", "grade_point": "467.876", "max_golden_ikura_num": 200, "avg_golden_ikura_num": "116.145", "is_clear_by_rate": [356, 288, 203, 137], "is_failure_by_rate": [280, 244, 162, 107], "failure_wave": [85, 82, 119], "shifts_worked": 652}, {"play_time": "2023-05-22T17:00:00.000Z", "grade_point": "431.99", "max_golden_ikura_num": 199, "avg_golden_ikura_num": "114.921", "is_clear_by_rate": [450, 342, 222, 137], "is_failure_by_rate": [304, 248, 175, 105], "failure_wave": [75, 88, 150], "shifts_worked": 779}, {"play_time": "2023-05-22T16:30:00.000Z", "grade_point": "403.583", "max_golden_ikura_num": 213, "avg_golden_ikura_num": "113.932", "is_clear_by_rate": [537, 384, 250, 146], "is_failure_by_rate": [354, 277, 179, 85], "failure_wave": [83, 122, 154], "shifts_worked": 907}, {"play_time": "2023-05-22T16:00:00.000Z", "grade_point": "400.117", "max_golden_ikura_num": 197, "avg_golden_ikura_num": "114.875", "is_clear_by_rate": [616, 422, 278, 157], "is_failure_by_rate": [388, 301, 199, 108], "failure_wave": [109, 130, 158], "shifts_worked": 1027}, {"play_time": "2023-05-22T15:30:00.000Z", "grade_point": "358.855", "max_golden_ikura_num": 236, "avg_golden_ikura_num": "113.48", "is_clear_by_rate": [856, 592, 352, 170], "is_failure_by_rate": [508, 371, 218, 112], "failure_wave": [144, 173, 217], "shifts_worked": 1419}, {"play_time": "2023-05-22T15:00:00.000Z", "grade_point": "329.244", "max_golden_ikura_num": 233, "avg_golden_ikura_num": "112.203", "is_clear_by_rate": [1042, 671, 376, 186], "is_failure_by_rate": [613, 409, 244, 133], "failure_wave": [156, 199, 292], "shifts_worked": 1745}, {"play_time": "2023-05-22T14:30:00.000Z", "grade_point": "300.159", "max_golden_ikura_num": 220, "avg_golden_ikura_num": "111.81", "is_clear_by_rate": [1378, 832, 429, 188], "is_failure_by_rate": [731, 447, 250, 128], "failure_wave": [170, 230, 374], "shifts_worked": 2231}, {"play_time": "2023-05-22T14:00:00.000Z", "grade_point": "279.3", "max_golden_ikura_num": 208, "avg_golden_ikura_num": "111.403", "is_clear_by_rate": [1492, 828, 393, 172], "is_failure_by_rate": [759, 466, 246, 123], "failure_wave": [159, 246, 400], "shifts_worked": 2365}, {"play_time": "2023-05-22T13:30:00.000Z", "grade_point": "273.39", "max_golden_ikura_num": 201, "avg_golden_ikura_num": "112.615", "is_clear_by_rate": [1852, 1045, 483, 206], "is_failure_by_rate": [800, 443, 235, 105], "failure_wave": [176, 258, 416], "shifts_worked": 2782}, {"play_time": "2023-05-22T13:00:00.000Z", "grade_point": "248.58", "max_golden_ikura_num": 203, "avg_golden_ikura_num": "112.246", "is_clear_by_rate": [1879, 906, 398, 172], "is_failure_by_rate": [839, 458, 212, 103], "failure_wave": [223, 263, 403], "shifts_worked": 2848}, {"play_time": "2023-05-22T12:30:00.000Z", "grade_point": "245.596", "max_golden_ikura_num": 224, "avg_golden_ikura_num": "112.935", "is_clear_by_rate": [1812, 801, 366, 145], "is_failure_by_rate": [716, 407, 202, 92], "failure_wave": [161, 236, 355], "shifts_worked": 2626}, {"play_time": "2023-05-22T12:00:00.000Z", "grade_point": "231.743", "max_golden_ikura_num": 203, "avg_golden_ikura_num": "111.621", "is_clear_by_rate": [1519, 632, 292, 110], "is_failure_by_rate": [561, 292, 163, 87], "failure_wave": [141, 192, 263], "shifts_worked": 2175}, {"play_time": "2023-05-22T11:30:00.000Z", "grade_point": "243.871", "max_golden_ikura_num": 205, "avg_golden_ikura_num": "111.726", "is_clear_by_rate": [1227, 566, 285, 121], "is_failure_by_rate": [476, 260, 130, 51], "failure_wave": [129, 169, 216], "shifts_worked": 1803}, {"play_time": "2023-05-22T11:00:00.000Z", "grade_point": "251.013", "max_golden_ikura_num": 202, "avg_golden_ikura_num": "112.711", "is_clear_by_rate": [1023, 457, 237, 93], "is_failure_by_rate": [406, 238, 119, 54], "failure_wave": [92, 138, 189], "shifts_worked": 1476}, {"play_time": "2023-05-22T10:30:00.000Z", "grade_point": "255.957", "max_golden_ikura_num": 206, "avg_golden_ikura_num": "111.597", "is_clear_by_rate": [839, 396, 217, 77], "is_failure_by_rate": [363, 211, 119, 64], "failure_wave": [89, 111, 182], "shifts_worked": 1265}, {"play_time": "2023-05-22T10:00:00.000Z", "grade_point": "271.101", "max_golden_ikura_num": 182, "avg_golden_ikura_num": "112.833", "is_clear_by_rate": [714, 353, 178, 74], "is_failure_by_rate": [257, 169, 93, 46], "failure_wave": [72, 82, 124], "shifts_worked": 1013}, {"play_time": "2023-05-22T09:30:00.000Z", "grade_point": "287.414", "max_golden_ikura_num": 191, "avg_golden_ikura_num": "112.914", "is_clear_by_rate": [761, 433, 213, 80], "is_failure_by_rate": [273, 183, 100, 44], "failure_wave": [70, 88, 136], "shifts_worked": 1071}, {"play_time": "2023-05-22T09:00:00.000Z", "grade_point": "284.75", "max_golden_ikura_num": 214, "avg_golden_ikura_num": "113.462", "is_clear_by_rate": [779, 411, 210, 90], "is_failure_by_rate": [282, 201, 103, 43], "failure_wave": [62, 110, 128], "shifts_worked": 1098}, {"play_time": "2023-05-22T08:30:00.000Z", "grade_point": "287.794", "max_golden_ikura_num": 197, "avg_golden_ikura_num": "114.359", "is_clear_by_rate": [796, 450, 227, 93], "is_failure_by_rate": [282, 186, 83, 43], "failure_wave": [64, 88, 141], "shifts_worked": 1104}, {"play_time": "2023-05-22T08:00:00.000Z", "grade_point": "293.475", "max_golden_ikura_num": 219, "avg_golden_ikura_num": "113.907", "is_clear_by_rate": [706, 415, 188, 86], "is_failure_by_rate": [292, 206, 100, 43], "failure_wave": [59, 93, 152], "shifts_worked": 1023}, {"play_time": "2023-05-22T07:30:00.000Z", "grade_point": "307.554", "max_golden_ikura_num": 234, "avg_golden_ikura_num": "116.039", "is_clear_by_rate": [768, 492, 216, 75], "is_failure_by_rate": [284, 200, 101, 45], "failure_wave": [65, 83, 140], "shifts_worked": 1065}, {"play_time": "2023-05-22T07:00:00.000Z", "grade_point": "304.213", "max_golden_ikura_num": 185, "avg_golden_ikura_num": "113.949", "is_clear_by_rate": [779, 478, 214, 69], "is_failure_by_rate": [308, 202, 99, 41], "failure_wave": [66, 100, 146], "shifts_worked": 1099}, {"play_time": "2023-05-22T06:30:00.000Z", "grade_point": "292.943", "max_golden_ikura_num": 200, "avg_golden_ikura_num": "113.474", "is_clear_by_rate": [778, 479, 197, 59], "is_failure_by_rate": [302, 199, 105, 35], "failure_wave": [71, 99, 145], "shifts_worked": 1111}, {"play_time": "2023-05-22T06:00:00.000Z", "grade_point": "277.802", "max_golden_ikura_num": 168, "avg_golden_ikura_num": "113.904", "is_clear_by_rate": [706, 419, 174, 68], "is_failure_by_rate": [299, 184, 86, 33], "failure_wave": [69, 101, 153], "shifts_worked": 1051}, {"play_time": "2023-05-22T05:30:00.000Z", "grade_point": "269.488", "max_golden_ikura_num": 172, "avg_golden_ikura_num": "112.537", "is_clear_by_rate": [727, 421, 180, 67], "is_failure_by_rate": [287, 177, 75, 34], "failure_wave": [63, 90, 153], "shifts_worked": 1064}, {"play_time": "2023-05-22T05:00:00.000Z", "grade_point": "265.814", "max_golden_ikura_num": 193, "avg_golden_ikura_num": "112.646", "is_clear_by_rate": [676, 365, 153, 53], "is_failure_by_rate": [280, 190, 86, 42], "failure_wave": [66, 98, 145], "shifts_worked": 1001}, {"play_time": "2023-05-22T04:30:00.000Z", "grade_point": "273.218", "max_golden_ikura_num": 182, "avg_golden_ikura_num": "113.493", "is_clear_by_rate": [593, 334, 134, 48], "is_failure_by_rate": [243, 149, 73, 23], "failure_wave": [53, 83, 119], "shifts_worked": 856}, {"play_time": "2023-05-22T04:00:00.000Z", "grade_point": "259.802", "max_golden_ikura_num": 174, "avg_golden_ikura_num": "112.556", "is_clear_by_rate": [563, 272, 113, 41], "is_failure_by_rate": [226, 153, 69, 20], "failure_wave": [55, 80, 96], "shifts_worked": 810}, {"play_time": "2023-05-22T03:30:00.000Z", "grade_point": "239.837", "max_golden_ikura_num": 189, "avg_golden_ikura_num": "111.893", "is_clear_by_rate": [623, 294, 116, 35], "is_failure_by_rate": [240, 143, 61, 17], "failure_wave": [46, 78, 129], "shifts_worked": 891}, {"play_time": "2023-05-22T03:00:00.000Z", "grade_point": "240.213", "max_golden_ikura_num": 175, "avg_golden_ikura_num": "110.831", "is_clear_by_rate": [567, 264, 101, 32], "is_failure_by_rate": [224, 142, 50, 17], "failure_wave": [52, 80, 107], "shifts_worked": 820}, {"play_time": "2023-05-22T02:30:00.000Z", "grade_point": "243.287", "max_golden_ikura_num": 164, "avg_golden_ikura_num": "111.678", "is_clear_by_rate": [545, 287, 95, 35], "is_failure_by_rate": [213, 118, 44, 20], "failure_wave": [45, 70, 108], "shifts_worked": 791}, {"play_time": "2023-05-22T02:00:00.000Z", "grade_point": "228.154", "max_golden_ikura_num": 171, "avg_golden_ikura_num": "111.046", "is_clear_by_rate": [566, 270, 94, 28], "is_failure_by_rate": [207, 116, 39, 19], "failure_wave": [47, 68, 114], "shifts_worked": 818}, {"play_time": "2023-05-22T01:30:00.000Z", "grade_point": "204.768", "max_golden_ikura_num": 176, "avg_golden_ikura_num": "110.832", "is_clear_by_rate": [590, 256, 78, 21], "is_failure_by_rate": [200, 99, 35, 18], "failure_wave": [48, 73, 106], "shifts_worked": 840}, {"play_time": "2023-05-22T01:00:00.000Z", "grade_point": "181.253", "max_golden_ikura_num": 184, "avg_golden_ikura_num": "110.578", "is_clear_by_rate": [533, 191, 47, 13], "is_failure_by_rate": [180, 89, 18, 6], "failure_wave": [44, 74, 82], "shifts_worked": 750}, {"play_time": "2023-05-22T00:30:00.000Z", "grade_point": "177.329", "max_golden_ikura_num": 160, "avg_golden_ikura_num": "109.941", "is_clear_by_rate": [461, 138, 34, 12], "is_failure_by_rate": [158, 74, 25, 12], "failure_wave": [41, 53, 74], "shifts_worked": 644}, {"play_time": "2023-05-22T00:00:00.000Z", "grade_point": "199.73", "max_golden_ikura_num": 176, "avg_golden_ikura_num": "110.97", "is_clear_by_rate": [390, 130, 49, 21], "is_failure_by_rate": [126, 67, 32, 14], "failure_wave": [27, 42, 67], "shifts_worked": 537}, {"play_time": "2023-05-21T23:30:00.000Z", "grade_point": "208.915", "max_golden_ikura_num": 168, "avg_golden_ikura_num": "108.883", "is_clear_by_rate": [345, 128, 47, 21], "is_failure_by_rate": [118, 59, 30, 19], "failure_wave": [20, 31, 74], "shifts_worked": 484}, {"play_time": "2023-05-21T23:00:00.000Z", "grade_point": "246.866", "max_golden_ikura_num": 184, "avg_golden_ikura_num": "111.132", "is_clear_by_rate": [252, 91, 40, 26], "is_failure_by_rate": [105, 67, 34, 22], "failure_wave": [11, 46, 53], "shifts_worked": 367}, {"play_time": "2023-05-21T22:30:00.000Z", "grade_point": "268.783", "max_golden_ikura_num": 173, "avg_golden_ikura_num": "111.302", "is_clear_by_rate": [206, 85, 47, 37], "is_failure_by_rate": [85, 50, 22, 17], "failure_wave": [15, 39, 35], "shifts_worked": 304}, {"play_time": "2023-05-21T22:00:00.000Z", "grade_point": "276.007", "max_golden_ikura_num": 167, "avg_golden_ikura_num": "111.936", "is_clear_by_rate": [191, 92, 57, 40], "is_failure_by_rate": [77, 43, 27, 14], "failure_wave": [23, 28, 39], "shifts_worked": 293}, {"play_time": "2023-05-21T21:30:00.000Z", "grade_point": "290.061", "max_golden_ikura_num": 193, "avg_golden_ikura_num": "113.167", "is_clear_by_rate": [217, 114, 66, 46], "is_failure_by_rate": [91, 58, 31, 17], "failure_wave": [25, 29, 45], "shifts_worked": 326}, {"play_time": "2023-05-21T21:00:00.000Z", "grade_point": "310.235", "max_golden_ikura_num": 172, "avg_golden_ikura_num": "114.603", "is_clear_by_rate": [233, 132, 77, 44], "is_failure_by_rate": [97, 74, 40, 15], "failure_wave": [23, 32, 46], "shifts_worked": 340}, {"play_time": "2023-05-21T20:30:00.000Z", "grade_point": "292.997", "max_golden_ikura_num": 196, "avg_golden_ikura_num": "114.952", "is_clear_by_rate": [245, 147, 84, 42], "is_failure_by_rate": [92, 58, 23, 5], "failure_wave": [23, 35, 38], "shifts_worked": 347}, {"play_time": "2023-05-21T20:00:00.000Z", "grade_point": "285.795", "max_golden_ikura_num": 168, "avg_golden_ikura_num": "114.918", "is_clear_by_rate": [254, 153, 83, 33], "is_failure_by_rate": [95, 56, 26, 3], "failure_wave": [18, 33, 44], "shifts_worked": 352}, {"play_time": "2023-05-21T19:30:00.000Z", "grade_point": "302.682", "max_golden_ikura_num": 187, "avg_golden_ikura_num": "115.231", "is_clear_by_rate": [286, 191, 104, 10], "is_failure_by_rate": [113, 87, 28, 0], "failure_wave": [24, 29, 60], "shifts_worked": 399}, {"play_time": "2023-05-21T19:00:00.000Z", "grade_point": "278", "max_golden_ikura_num": 182, "avg_golden_ikura_num": "114.422", "is_clear_by_rate": [331, 218, 106, 0], "is_failure_by_rate": [137, 88, 24, 0], "failure_wave": [28, 44, 66], "shifts_worked": 470}, {"play_time": "2023-05-21T18:30:00.000Z", "grade_point": "243.628", "max_golden_ikura_num": 172, "avg_golden_ikura_num": "114.237", "is_clear_by_rate": [427, 272, 78, 0], "is_failure_by_rate": [140, 83, 11, 0], "failure_wave": [39, 41, 64], "shifts_worked": 583}, {"play_time": "2023-05-21T18:00:00.000Z", "grade_point": "202.695", "max_golden_ikura_num": 179, "avg_golden_ikura_num": "113.483", "is_clear_by_rate": [539, 295, 6, 0], "is_failure_by_rate": [181, 94, 1, 0], "failure_wave": [32, 85, 76], "shifts_worked": 742}, {"play_time": "2023-05-21T17:30:00.000Z", "grade_point": "177.927", "max_golden_ikura_num": 165, "avg_golden_ikura_num": "111.708", "is_clear_by_rate": [864, 477, 0, 0], "is_failure_by_rate": [258, 127, 0, 0], "failure_wave": [60, 87, 136], "shifts_worked": 1177}, {"play_time": "2023-05-21T17:00:00.000Z", "grade_point": "136.649", "max_golden_ikura_num": 175, "avg_golden_ikura_num": "111.478", "is_clear_by_rate": [1158, 295, 0, 0], "is_failure_by_rate": [306, 52, 0, 0], "failure_wave": [58, 127, 154], "shifts_worked": 1537}, {"play_time": "2023-05-21T16:30:00.000Z", "grade_point": "97.887", "max_golden_ikura_num": 180, "avg_golden_ikura_num": "110.929", "is_clear_by_rate": [1729, 3, 0, 0], "is_failure_by_rate": [348, 0, 0, 0], "failure_wave": [96, 106, 184], "shifts_worked": 2165}, {"play_time": "2023-05-21T16:00:00.000Z", "grade_point": "47.605", "max_golden_ikura_num": 178, "avg_golden_ikura_num": "110.536", "is_clear_by_rate": [2354, 0, 0, 0], "is_failure_by_rate": [317, 0, 0, 0], "failure_wave": [73, 136, 173], "shifts_worked": 2864}], "waves": [[{"water_level": 2, "event_type": 0, "occurrence": 28208, "is_clear": 25868, "golden_ikura_num": 90}, {"water_level": 0, "event_type": 0, "occurrence": 28027, "is_clear": 24552, "golden_ikura_num": 72}, {"water_level": 1, "event_type": 0, "occurrence": 85035, "is_clear": 73725, "golden_ikura_num": 84}], [{"water_level": 1, "event_type": 1, "occurrence": 4345, "is_clear": 3099, "golden_ikura_num": 72}, {"water_level": 2, "event_type": 1, "occurrence": 1417, "is_clear": 753, "golden_ikura_num": 55}], [{"water_level": 2, "event_type": 2, "occurrence": 1425, "is_clear": 1424, "golden_ikura_num": 88}, {"water_level": 1, "event_type": 2, "occurrence": 4325, "is_clear": 4246, "golden_ikura_num": 77}], [{"water_level": 1, "event_type": 3, "occurrence": 4346, "is_clear": 3923, "golden_ikura_num": 77}, {"water_level": 2, "event_type": 3, "occurrence": 1439, "is_clear": 1080, "golden_ikura_num": 76}], [{"water_level": 0, "event_type": 4, "occurrence": 1091, "is_clear": 1077, "golden_ikura_num": 84}, {"water_level": 1, "event_type": 4, "occurrence": 3468, "is_clear": 3444, "golden_ikura_num": 82}, {"water_level": 2, "event_type": 4, "occurrence": 1182, "is_clear": 1175, "golden_ikura_num": 99}], [{"water_level": 1, "event_type": 5, "occurrence": 3405, "is_clear": 3147, "golden_ikura_num": 82}, {"water_level": 2, "event_type": 5, "occurrence": 1116, "is_clear": 1024, "golden_ikura_num": 88}, {"water_level": 0, "event_type": 5, "occurrence": 1130, "is_clear": 1047, "golden_ikura_num": 77}], [{"water_level": 0, "event_type": 6, "occurrence": 5827, "is_clear": 5635, "golden_ikura_num": 72}], [{"water_level": 0, "event_type": 7, "occurrence": 5774, "is_clear": 5761, "golden_ikura_num": 68}], [{"water_level": 1, "event_type": 8, "occurrence": 4289, "is_clear": 4231, "golden_ikura_num": 73}, {"water_level": 2, "event_type": 8, "occurrence": 1463, "is_clear": 1457, "golden_ikura_num": 95}]]}