{"distribution": {"golden_ikura_num_avg": "104.571", "golden_ikura_num_std": "30.493", "ikura_num_avg": "3765.429", "ikura_num_std": "1351.326"}, "golden_ikura_num": [{"golden_ikura_num": 210, "count": 8}, {"golden_ikura_num": 185, "count": 4}, {"golden_ikura_num": 180, "count": 13}, {"golden_ikura_num": 175, "count": 16}, {"golden_ikura_num": 170, "count": 14}, {"golden_ikura_num": 165, "count": 30}, {"golden_ikura_num": 160, "count": 45}, {"golden_ikura_num": 155, "count": 44}, {"golden_ikura_num": 150, "count": 57}, {"golden_ikura_num": 145, "count": 64}, {"golden_ikura_num": 140, "count": 139}, {"golden_ikura_num": 135, "count": 181}, {"golden_ikura_num": 130, "count": 160}, {"golden_ikura_num": 125, "count": 250}, {"golden_ikura_num": 120, "count": 335}, {"golden_ikura_num": 115, "count": 359}, {"golden_ikura_num": 110, "count": 447}, {"golden_ikura_num": 105, "count": 489}, {"golden_ikura_num": 100, "count": 368}, {"golden_ikura_num": 95, "count": 345}, {"golden_ikura_num": 90, "count": 368}, {"golden_ikura_num": 85, "count": 229}, {"golden_ikura_num": 80, "count": 123}, {"golden_ikura_num": 75, "count": 71}, {"golden_ikura_num": 70, "count": 58}, {"golden_ikura_num": 65, "count": 48}, {"golden_ikura_num": 60, "count": 30}, {"golden_ikura_num": 55, "count": 64}, {"golden_ikura_num": 50, "count": 56}, {"golden_ikura_num": 45, "count": 71}, {"golden_ikura_num": 40, "count": 56}, {"golden_ikura_num": 35, "count": 25}, {"golden_ikura_num": 30, "count": 13}, {"golden_ikura_num": 25, "count": 9}, {"golden_ikura_num": 20, "count": 73}, {"golden_ikura_num": 15, "count": 72}, {"golden_ikura_num": 10, "count": 13}, {"golden_ikura_num": 0, "count": 1}], "grade_point": [{"grade_id": 8, "grade_point": 999, "count": 14}, {"grade_id": 8, "grade_point": 800, "count": 7}, {"grade_id": 8, "grade_point": 600, "count": 10}, {"grade_id": 8, "grade_point": 400, "count": 41}, {"grade_id": 8, "grade_point": 200, "count": 58}, {"grade_id": 8, "grade_point": 0, "count": 70}, {"grade_id": 7, "grade_point": 0, "count": 1}, {"grade_id": 6, "grade_point": 0, "count": 1}], "status": [{"play_time": "2023-10-02T16:00:00.000Z", "grade_point": "345", "max_golden_ikura_num": 112, "avg_golden_ikura_num": "103", "is_clear_by_rate": [2, 2, 1, 0], "is_failure_by_rate": [0, 0, 0, 0], "failure_wave": [0, 0, 0], "shifts_worked": 2}, {"play_time": "2023-10-02T15:30:00.000Z", "grade_point": "436.78", "max_golden_ikura_num": 147, "avg_golden_ikura_num": "111.079", "is_clear_by_rate": [34, 30, 23, 16], "is_failure_by_rate": [19, 18, 7, 3], "failure_wave": [5, 3, 13], "shifts_worked": 59}, {"play_time": "2023-10-02T15:00:00.000Z", "grade_point": "432.124", "max_golden_ikura_num": 168, "avg_golden_ikura_num": "113.644", "is_clear_by_rate": [69, 67, 39, 22], "is_failure_by_rate": [36, 32, 13, 8], "failure_wave": [7, 15, 18], "shifts_worked": 113}, {"play_time": "2023-10-02T14:30:00.000Z", "grade_point": "390.833", "max_golden_ikura_num": 212, "avg_golden_ikura_num": "116.862", "is_clear_by_rate": [115, 102, 55, 27], "is_failure_by_rate": [50, 38, 16, 10], "failure_wave": [14, 17, 27], "shifts_worked": 174}, {"play_time": "2023-10-02T14:00:00.000Z", "grade_point": "359.67", "max_golden_ikura_num": 171, "avg_golden_ikura_num": "115.854", "is_clear_by_rate": [160, 126, 60, 35], "is_failure_by_rate": [46, 30, 13, 7], "failure_wave": [11, 16, 21], "shifts_worked": 212}, {"play_time": "2023-10-02T13:30:00.000Z", "grade_point": "340.839", "max_golden_ikura_num": 179, "avg_golden_ikura_num": "119.417", "is_clear_by_rate": [258, 184, 77, 43], "is_failure_by_rate": [62, 41, 12, 5], "failure_wave": [23, 15, 25], "shifts_worked": 322}, {"play_time": "2023-10-02T13:00:00.000Z", "grade_point": "308.763", "max_golden_ikura_num": 185, "avg_golden_ikura_num": "117.483", "is_clear_by_rate": [234, 148, 67, 37], "is_failure_by_rate": [61, 31, 12, 3], "failure_wave": [8, 22, 33], "shifts_worked": 299}, {"play_time": "2023-10-02T12:30:00.000Z", "grade_point": "281.566", "max_golden_ikura_num": 160, "avg_golden_ikura_num": "114.702", "is_clear_by_rate": [243, 133, 68, 42], "is_failure_by_rate": [46, 18, 9, 5], "failure_wave": [9, 18, 22], "shifts_worked": 297}, {"play_time": "2023-10-02T12:00:00.000Z", "grade_point": "267.788", "max_golden_ikura_num": 179, "avg_golden_ikura_num": "115.868", "is_clear_by_rate": [214, 114, 67, 45], "is_failure_by_rate": [48, 15, 4, 2], "failure_wave": [8, 16, 25], "shifts_worked": 269}, {"play_time": "2023-10-02T11:30:00.000Z", "grade_point": "302.436", "max_golden_ikura_num": 169, "avg_golden_ikura_num": "119.223", "is_clear_by_rate": [182, 129, 76, 25], "is_failure_by_rate": [48, 16, 5, 1], "failure_wave": [10, 19, 21], "shifts_worked": 234}, {"play_time": "2023-10-02T11:00:00.000Z", "grade_point": "301.737", "max_golden_ikura_num": 188, "avg_golden_ikura_num": "119.301", "is_clear_by_rate": [172, 125, 75, 0], "is_failure_by_rate": [33, 19, 5, 0], "failure_wave": [14, 7, 19], "shifts_worked": 213}, {"play_time": "2023-10-02T10:30:00.000Z", "grade_point": "259.068", "max_golden_ikura_num": 212, "avg_golden_ikura_num": "118.337", "is_clear_by_rate": [183, 120, 63, 0], "is_failure_by_rate": [30, 15, 3, 0], "failure_wave": [4, 13, 19], "shifts_worked": 220}, {"play_time": "2023-10-02T10:00:00.000Z", "grade_point": "232.799", "max_golden_ikura_num": 170, "avg_golden_ikura_num": "117.57", "is_clear_by_rate": [176, 124, 13, 0], "is_failure_by_rate": [24, 8, 1, 0], "failure_wave": [13, 12, 5], "shifts_worked": 209}, {"play_time": "2023-10-02T09:30:00.000Z", "grade_point": "207.699", "max_golden_ikura_num": 184, "avg_golden_ikura_num": "116.812", "is_clear_by_rate": [190, 133, 0, 0], "is_failure_by_rate": [39, 16, 0, 0], "failure_wave": [9, 13, 20], "shifts_worked": 239}, {"play_time": "2023-10-02T09:00:00.000Z", "grade_point": "162.964", "max_golden_ikura_num": 178, "avg_golden_ikura_num": "113.485", "is_clear_by_rate": [219, 101, 0, 0], "is_failure_by_rate": [45, 10, 0, 0], "failure_wave": [7, 13, 28], "shifts_worked": 275}, {"play_time": "2023-10-02T08:30:00.000Z", "grade_point": "110.86", "max_golden_ikura_num": 161, "avg_golden_ikura_num": "111.25", "is_clear_by_rate": [272, 6, 0, 0], "is_failure_by_rate": [24, 0, 0, 0], "failure_wave": [7, 8, 13], "shifts_worked": 308}, {"play_time": "2023-10-02T08:00:00.000Z", "grade_point": "55.584", "max_golden_ikura_num": 165, "avg_golden_ikura_num": "110.604", "is_clear_by_rate": [280, 0, 0, 0], "is_failure_by_rate": [25, 0, 0, 0], "failure_wave": [4, 12, 13], "shifts_worked": 317}], "waves": [[{"water_level": 2, "event_type": 0, "occurrence": 1542, "is_clear": 1468, "golden_ikura_num": 68}, {"water_level": 0, "event_type": 0, "occurrence": 1608, "is_clear": 1532, "golden_ikura_num": 62}, {"water_level": 1, "event_type": 0, "occurrence": 4933, "is_clear": 4480, "golden_ikura_num": 64}], [{"water_level": 1, "event_type": 1, "occurrence": 279, "is_clear": 245, "golden_ikura_num": 50}, {"water_level": 2, "event_type": 1, "occurrence": 77, "is_clear": 69, "golden_ikura_num": 69}], [{"water_level": 2, "event_type": 2, "occurrence": 86, "is_clear": 86, "golden_ikura_num": 85}, {"water_level": 1, "event_type": 2, "occurrence": 274, "is_clear": 271, "golden_ikura_num": 85}], [{"water_level": 1, "event_type": 3, "occurrence": 237, "is_clear": 229, "golden_ikura_num": 60}, {"water_level": 2, "event_type": 3, "occurrence": 71, "is_clear": 62, "golden_ikura_num": 68}], [{"water_level": 0, "event_type": 4, "occurrence": 65, "is_clear": 65, "golden_ikura_num": 65}, {"water_level": 1, "event_type": 4, "occurrence": 189, "is_clear": 187, "golden_ikura_num": 71}, {"water_level": 2, "event_type": 4, "occurrence": 62, "is_clear": 62, "golden_ikura_num": 83}], [{"water_level": 1, "event_type": 5, "occurrence": 192, "is_clear": 184, "golden_ikura_num": 71}, {"water_level": 2, "event_type": 5, "occurrence": 69, "is_clear": 63, "golden_ikura_num": 76}, {"water_level": 0, "event_type": 5, "occurrence": 89, "is_clear": 87, "golden_ikura_num": 64}], [{"water_level": 0, "event_type": 6, "occurrence": 354, "is_clear": 345, "golden_ikura_num": 57}], [{"water_level": 0, "event_type": 7, "occurrence": 346, "is_clear": 346, "golden_ikura_num": 66}], [{"water_level": 1, "event_type": 8, "occurrence": 218, "is_clear": 216, "golden_ikura_num": 88}, {"water_level": 2, "event_type": 8, "occurrence": 70, "is_clear": 70, "golden_ikura_num": 91}]]}