{"distribution": {"golden_ikura_num_avg": "112.995", "golden_ikura_num_std": "32.037", "ikura_num_avg": "4178.142", "ikura_num_std": "1362.806"}, "golden_ikura_num": [{"golden_ikura_num": 230, "count": 4}, {"golden_ikura_num": 220, "count": 8}, {"golden_ikura_num": 215, "count": 3}, {"golden_ikura_num": 210, "count": 4}, {"golden_ikura_num": 205, "count": 24}, {"golden_ikura_num": 200, "count": 8}, {"golden_ikura_num": 195, "count": 13}, {"golden_ikura_num": 190, "count": 28}, {"golden_ikura_num": 185, "count": 24}, {"golden_ikura_num": 180, "count": 42}, {"golden_ikura_num": 175, "count": 51}, {"golden_ikura_num": 170, "count": 69}, {"golden_ikura_num": 165, "count": 115}, {"golden_ikura_num": 160, "count": 181}, {"golden_ikura_num": 155, "count": 189}, {"golden_ikura_num": 150, "count": 258}, {"golden_ikura_num": 145, "count": 361}, {"golden_ikura_num": 140, "count": 500}, {"golden_ikura_num": 135, "count": 592}, {"golden_ikura_num": 130, "count": 723}, {"golden_ikura_num": 125, "count": 834}, {"golden_ikura_num": 120, "count": 963}, {"golden_ikura_num": 115, "count": 1053}, {"golden_ikura_num": 110, "count": 964}, {"golden_ikura_num": 105, "count": 917}, {"golden_ikura_num": 100, "count": 725}, {"golden_ikura_num": 95, "count": 655}, {"golden_ikura_num": 90, "count": 453}, {"golden_ikura_num": 85, "count": 305}, {"golden_ikura_num": 80, "count": 201}, {"golden_ikura_num": 75, "count": 102}, {"golden_ikura_num": 70, "count": 87}, {"golden_ikura_num": 65, "count": 62}, {"golden_ikura_num": 60, "count": 120}, {"golden_ikura_num": 55, "count": 121}, {"golden_ikura_num": 50, "count": 151}, {"golden_ikura_num": 45, "count": 99}, {"golden_ikura_num": 40, "count": 59}, {"golden_ikura_num": 35, "count": 33}, {"golden_ikura_num": 30, "count": 24}, {"golden_ikura_num": 25, "count": 46}, {"golden_ikura_num": 20, "count": 187}, {"golden_ikura_num": 15, "count": 80}, {"golden_ikura_num": 10, "count": 39}, {"golden_ikura_num": 5, "count": 20}, {"golden_ikura_num": 0, "count": 17}], "grade_point": [{"grade_id": 8, "grade_point": 999, "count": 74}, {"grade_id": 8, "grade_point": 800, "count": 18}, {"grade_id": 8, "grade_point": 600, "count": 31}, {"grade_id": 8, "grade_point": 400, "count": 56}, {"grade_id": 8, "grade_point": 200, "count": 119}, {"grade_id": 8, "grade_point": 0, "count": 98}, {"grade_id": 7, "grade_point": 0, "count": 1}, {"grade_id": 6, "grade_point": 0, "count": 1}], "status": [{"play_time": "2023-10-12T05:00:00.000Z", "grade_point": "587.581", "max_golden_ikura_num": 199, "avg_golden_ikura_num": "133.833", "is_clear_by_rate": [12, 11, 9, 4], "is_failure_by_rate": [19, 17, 14, 10], "failure_wave": [9, 2, 8], "shifts_worked": 31}, {"play_time": "2023-10-12T04:30:00.000Z", "grade_point": "572.971", "max_golden_ikura_num": 206, "avg_golden_ikura_num": "135.324", "is_clear_by_rate": [37, 36, 26, 18], "is_failure_by_rate": [32, 31, 26, 9], "failure_wave": [18, 5, 9], "shifts_worked": 69}, {"play_time": "2023-10-12T04:00:00.000Z", "grade_point": "637.794", "max_golden_ikura_num": 207, "avg_golden_ikura_num": "134.304", "is_clear_by_rate": [46, 46, 39, 26], "is_failure_by_rate": [22, 22, 14, 9], "failure_wave": [10, 5, 7], "shifts_worked": 68}, {"play_time": "2023-10-12T03:30:00.000Z", "grade_point": "674.73", "max_golden_ikura_num": 157, "avg_golden_ikura_num": "130.042", "is_clear_by_rate": [24, 23, 20, 18], "is_failure_by_rate": [13, 12, 11, 10], "failure_wave": [3, 2, 8], "shifts_worked": 37}, {"play_time": "2023-10-12T03:00:00.000Z", "grade_point": "701.163", "max_golden_ikura_num": 189, "avg_golden_ikura_num": "135.939", "is_clear_by_rate": [33, 33, 32, 24], "is_failure_by_rate": [10, 10, 10, 5], "failure_wave": [1, 2, 7], "shifts_worked": 43}, {"play_time": "2023-10-12T02:30:00.000Z", "grade_point": "655.69", "max_golden_ikura_num": 180, "avg_golden_ikura_num": "125.179", "is_clear_by_rate": [36, 36, 33, 24], "is_failure_by_rate": [19, 19, 18, 14], "failure_wave": [5, 6, 8], "shifts_worked": 58}, {"play_time": "2023-10-12T02:00:00.000Z", "grade_point": "587.5", "max_golden_ikura_num": 161, "avg_golden_ikura_num": "123.167", "is_clear_by_rate": [45, 40, 39, 28], "is_failure_by_rate": [15, 15, 12, 9], "failure_wave": [2, 7, 9], "shifts_worked": 66}, {"play_time": "2023-10-12T01:30:00.000Z", "grade_point": "600.566", "max_golden_ikura_num": 156, "avg_golden_ikura_num": "116.368", "is_clear_by_rate": [36, 34, 31, 20], "is_failure_by_rate": [15, 13, 12, 10], "failure_wave": [6, 3, 6], "shifts_worked": 53}, {"play_time": "2023-10-12T01:00:00.000Z", "grade_point": "605.918", "max_golden_ikura_num": 156, "avg_golden_ikura_num": "116.567", "is_clear_by_rate": [30, 26, 24, 12], "is_failure_by_rate": [19, 19, 18, 16], "failure_wave": [7, 6, 6], "shifts_worked": 49}, {"play_time": "2023-10-12T00:30:00.000Z", "grade_point": "518.077", "max_golden_ikura_num": 154, "avg_golden_ikura_num": "118.29", "is_clear_by_rate": [31, 25, 22, 13], "is_failure_by_rate": [21, 17, 14, 10], "failure_wave": [9, 5, 7], "shifts_worked": 52}, {"play_time": "2023-10-12T00:00:00.000Z", "grade_point": "632.5", "max_golden_ikura_num": 150, "avg_golden_ikura_num": "118.737", "is_clear_by_rate": [19, 18, 14, 7], "is_failure_by_rate": [13, 12, 12, 9], "failure_wave": [1, 7, 5], "shifts_worked": 32}, {"play_time": "2023-10-11T23:30:00.000Z", "grade_point": "556.731", "max_golden_ikura_num": 145, "avg_golden_ikura_num": "114.917", "is_clear_by_rate": [12, 10, 8, 5], "is_failure_by_rate": [14, 12, 10, 6], "failure_wave": [2, 6, 6], "shifts_worked": 26}, {"play_time": "2023-10-11T23:00:00.000Z", "grade_point": "592.391", "max_golden_ikura_num": 156, "avg_golden_ikura_num": "116", "is_clear_by_rate": [12, 10, 9, 6], "is_failure_by_rate": [10, 9, 8, 7], "failure_wave": [4, 3, 4], "shifts_worked": 23}, {"play_time": "2023-10-11T22:30:00.000Z", "grade_point": "517.955", "max_golden_ikura_num": 129, "avg_golden_ikura_num": "102.5", "is_clear_by_rate": [5, 5, 4, 2], "is_failure_by_rate": [13, 13, 13, 9], "failure_wave": [1, 7, 6], "shifts_worked": 22}, {"play_time": "2023-10-11T22:00:00.000Z", "grade_point": "499.667", "max_golden_ikura_num": 132, "avg_golden_ikura_num": "110.25", "is_clear_by_rate": [6, 6, 6, 4], "is_failure_by_rate": [6, 6, 6, 5], "failure_wave": [1, 1, 5], "shifts_worked": 15}, {"play_time": "2023-10-11T21:30:00.000Z", "grade_point": "703.333", "max_golden_ikura_num": 155, "avg_golden_ikura_num": "122.8", "is_clear_by_rate": [5, 5, 5, 5], "is_failure_by_rate": [1, 1, 1, 1], "failure_wave": [0, 0, 1], "shifts_worked": 6}, {"play_time": "2023-10-11T21:00:00.000Z", "grade_point": "782.5", "max_golden_ikura_num": 128, "avg_golden_ikura_num": "111", "is_clear_by_rate": [4, 4, 4, 3], "is_failure_by_rate": [4, 4, 4, 4], "failure_wave": [1, 0, 3], "shifts_worked": 8}, {"play_time": "2023-10-11T20:30:00.000Z", "grade_point": "853.333", "max_golden_ikura_num": 141, "avg_golden_ikura_num": "128.167", "is_clear_by_rate": [6, 6, 6, 6], "is_failure_by_rate": [6, 6, 6, 6], "failure_wave": [1, 1, 4], "shifts_worked": 12}, {"play_time": "2023-10-11T20:00:00.000Z", "grade_point": "703.864", "max_golden_ikura_num": 154, "avg_golden_ikura_num": "114.167", "is_clear_by_rate": [12, 10, 10, 9], "is_failure_by_rate": [10, 9, 9, 9], "failure_wave": [2, 3, 5], "shifts_worked": 22}, {"play_time": "2023-10-11T19:30:00.000Z", "grade_point": "705.862", "max_golden_ikura_num": 138, "avg_golden_ikura_num": "116", "is_clear_by_rate": [13, 12, 11, 11], "is_failure_by_rate": [16, 15, 14, 14], "failure_wave": [4, 4, 8], "shifts_worked": 29}, {"play_time": "2023-10-11T19:00:00.000Z", "grade_point": "674.125", "max_golden_ikura_num": 142, "avg_golden_ikura_num": "119.083", "is_clear_by_rate": [24, 20, 20, 16], "is_failure_by_rate": [16, 16, 16, 16], "failure_wave": [4, 5, 7], "shifts_worked": 40}, {"play_time": "2023-10-11T18:30:00.000Z", "grade_point": "744.364", "max_golden_ikura_num": 172, "avg_golden_ikura_num": "124.9", "is_clear_by_rate": [30, 29, 27, 22], "is_failure_by_rate": [25, 25, 25, 25], "failure_wave": [8, 8, 9], "shifts_worked": 55}, {"play_time": "2023-10-11T18:00:00.000Z", "grade_point": "699.938", "max_golden_ikura_num": 169, "avg_golden_ikura_num": "120", "is_clear_by_rate": [45, 40, 37, 32], "is_failure_by_rate": [36, 36, 35, 32], "failure_wave": [4, 16, 16], "shifts_worked": 81}, {"play_time": "2023-10-11T17:30:00.000Z", "grade_point": "605.678", "max_golden_ikura_num": 207, "avg_golden_ikura_num": "124.747", "is_clear_by_rate": [75, 70, 59, 43], "is_failure_by_rate": [43, 42, 37, 23], "failure_wave": [5, 15, 23], "shifts_worked": 118}, {"play_time": "2023-10-11T17:00:00.000Z", "grade_point": "537.644", "max_golden_ikura_num": 205, "avg_golden_ikura_num": "124.633", "is_clear_by_rate": [108, 94, 80, 46], "is_failure_by_rate": [65, 61, 51, 31], "failure_wave": [11, 25, 29], "shifts_worked": 174}, {"play_time": "2023-10-11T16:30:00.000Z", "grade_point": "508.732", "max_golden_ikura_num": 213, "avg_golden_ikura_num": "125.946", "is_clear_by_rate": [145, 122, 95, 51], "is_failure_by_rate": [65, 64, 54, 30], "failure_wave": [9, 21, 35], "shifts_worked": 213}, {"play_time": "2023-10-11T16:00:00.000Z", "grade_point": "492.202", "max_golden_ikura_num": 205, "avg_golden_ikura_num": "121.056", "is_clear_by_rate": [161, 133, 102, 56], "is_failure_by_rate": [56, 50, 42, 22], "failure_wave": [7, 18, 31], "shifts_worked": 218}, {"play_time": "2023-10-11T15:30:00.000Z", "grade_point": "529.275", "max_golden_ikura_num": 222, "avg_golden_ikura_num": "128.096", "is_clear_by_rate": [193, 174, 135, 89], "is_failure_by_rate": [78, 69, 53, 35], "failure_wave": [22, 31, 25], "shifts_worked": 276}, {"play_time": "2023-10-11T15:00:00.000Z", "grade_point": "516.943", "max_golden_ikura_num": 217, "avg_golden_ikura_num": "126.824", "is_clear_by_rate": [197, 177, 146, 92], "is_failure_by_rate": [114, 99, 66, 49], "failure_wave": [19, 38, 58], "shifts_worked": 314}, {"play_time": "2023-10-11T14:30:00.000Z", "grade_point": "473.938", "max_golden_ikura_num": 221, "avg_golden_ikura_num": "125.622", "is_clear_by_rate": [299, 248, 184, 114], "is_failure_by_rate": [125, 110, 75, 50], "failure_wave": [31, 38, 65], "shifts_worked": 438}, {"play_time": "2023-10-11T14:00:00.000Z", "grade_point": "405.13", "max_golden_ikura_num": 216, "avg_golden_ikura_num": "123.25", "is_clear_by_rate": [320, 259, 167, 85], "is_failure_by_rate": [124, 97, 67, 43], "failure_wave": [43, 39, 55], "shifts_worked": 461}, {"play_time": "2023-10-11T13:30:00.000Z", "grade_point": "380.327", "max_golden_ikura_num": 190, "avg_golden_ikura_num": "121.092", "is_clear_by_rate": [346, 246, 138, 61], "is_failure_by_rate": [124, 86, 60, 33], "failure_wave": [25, 36, 64], "shifts_worked": 474}, {"play_time": "2023-10-11T13:00:00.000Z", "grade_point": "376.112", "max_golden_ikura_num": 199, "avg_golden_ikura_num": "120.711", "is_clear_by_rate": [319, 229, 126, 54], "is_failure_by_rate": [113, 85, 53, 33], "failure_wave": [30, 31, 53], "shifts_worked": 436}, {"play_time": "2023-10-11T12:30:00.000Z", "grade_point": "355.337", "max_golden_ikura_num": 205, "avg_golden_ikura_num": "122.354", "is_clear_by_rate": [289, 202, 115, 62], "is_failure_by_rate": [111, 73, 47, 27], "failure_wave": [37, 36, 51], "shifts_worked": 415}, {"play_time": "2023-10-11T12:00:00.000Z", "grade_point": "354.155", "max_golden_ikura_num": 206, "avg_golden_ikura_num": "123.704", "is_clear_by_rate": [257, 156, 100, 55], "is_failure_by_rate": [88, 55, 36, 15], "failure_wave": [16, 29, 47], "shifts_worked": 349}, {"play_time": "2023-10-11T11:30:00.000Z", "grade_point": "321.081", "max_golden_ikura_num": 188, "avg_golden_ikura_num": "121.212", "is_clear_by_rate": [174, 105, 68, 36], "is_failure_by_rate": [71, 43, 32, 22], "failure_wave": [24, 20, 36], "shifts_worked": 259}, {"play_time": "2023-10-11T11:00:00.000Z", "grade_point": "315.339", "max_golden_ikura_num": 190, "avg_golden_ikura_num": "120.577", "is_clear_by_rate": [150, 91, 60, 35], "is_failure_by_rate": [69, 50, 29, 17], "failure_wave": [21, 22, 37], "shifts_worked": 236}, {"play_time": "2023-10-11T10:30:00.000Z", "grade_point": "369.849", "max_golden_ikura_num": 191, "avg_golden_ikura_num": "118.059", "is_clear_by_rate": [129, 84, 61, 34], "is_failure_by_rate": [49, 41, 36, 29], "failure_wave": [25, 17, 21], "shifts_worked": 199}, {"play_time": "2023-10-11T10:00:00.000Z", "grade_point": "457.099", "max_golden_ikura_num": 172, "avg_golden_ikura_num": "120.263", "is_clear_by_rate": [108, 85, 67, 41], "is_failure_by_rate": [58, 46, 41, 27], "failure_wave": [22, 17, 28], "shifts_worked": 181}, {"play_time": "2023-10-11T09:30:00.000Z", "grade_point": "536.089", "max_golden_ikura_num": 208, "avg_golden_ikura_num": "129.467", "is_clear_by_rate": [137, 117, 93, 58], "is_failure_by_rate": [42, 38, 31, 15], "failure_wave": [8, 10, 24], "shifts_worked": 179}, {"play_time": "2023-10-11T09:00:00.000Z", "grade_point": "489.6", "max_golden_ikura_num": 216, "avg_golden_ikura_num": "128.607", "is_clear_by_rate": [143, 119, 94, 54], "is_failure_by_rate": [54, 45, 28, 20], "failure_wave": [16, 17, 22], "shifts_worked": 200}, {"play_time": "2023-10-11T08:30:00.000Z", "grade_point": "483.781", "max_golden_ikura_num": 200, "avg_golden_ikura_num": "128.966", "is_clear_by_rate": [147, 126, 85, 49], "is_failure_by_rate": [54, 43, 34, 24], "failure_wave": [16, 15, 23], "shifts_worked": 201}, {"play_time": "2023-10-11T08:00:00.000Z", "grade_point": "465.335", "max_golden_ikura_num": 206, "avg_golden_ikura_num": "126.431", "is_clear_by_rate": [137, 110, 72, 46], "is_failure_by_rate": [57, 48, 34, 23], "failure_wave": [9, 20, 28], "shifts_worked": 194}, {"play_time": "2023-10-11T07:30:00.000Z", "grade_point": "459.41", "max_golden_ikura_num": 211, "avg_golden_ikura_num": "130.507", "is_clear_by_rate": [142, 112, 75, 48], "is_failure_by_rate": [36, 27, 22, 15], "failure_wave": [8, 14, 14], "shifts_worked": 178}, {"play_time": "2023-10-11T07:00:00.000Z", "grade_point": "470.702", "max_golden_ikura_num": 230, "avg_golden_ikura_num": "129.614", "is_clear_by_rate": [132, 107, 80, 41], "is_failure_by_rate": [46, 34, 26, 22], "failure_wave": [11, 15, 20], "shifts_worked": 178}, {"play_time": "2023-10-11T06:30:00.000Z", "grade_point": "452.5", "max_golden_ikura_num": 216, "avg_golden_ikura_num": "130.051", "is_clear_by_rate": [137, 113, 72, 45], "is_failure_by_rate": [47, 38, 23, 11], "failure_wave": [8, 16, 23], "shifts_worked": 184}, {"play_time": "2023-10-11T06:00:00.000Z", "grade_point": "439.049", "max_golden_ikura_num": 206, "avg_golden_ikura_num": "123.583", "is_clear_by_rate": [144, 111, 77, 44], "is_failure_by_rate": [40, 33, 20, 17], "failure_wave": [8, 8, 24], "shifts_worked": 184}, {"play_time": "2023-10-11T05:30:00.000Z", "grade_point": "427.732", "max_golden_ikura_num": 194, "avg_golden_ikura_num": "123.094", "is_clear_by_rate": [127, 97, 60, 32], "is_failure_by_rate": [55, 47, 31, 22], "failure_wave": [12, 19, 25], "shifts_worked": 183}, {"play_time": "2023-10-11T05:00:00.000Z", "grade_point": "452.616", "max_golden_ikura_num": 193, "avg_golden_ikura_num": "124.7", "is_clear_by_rate": [100, 76, 56, 26], "is_failure_by_rate": [51, 43, 31, 24], "failure_wave": [10, 23, 18], "shifts_worked": 151}, {"play_time": "2023-10-11T04:30:00.000Z", "grade_point": "462.647", "max_golden_ikura_num": 192, "avg_golden_ikura_num": "122.189", "is_clear_by_rate": [93, 77, 50, 19], "is_failure_by_rate": [40, 35, 26, 20], "failure_wave": [5, 18, 18], "shifts_worked": 136}, {"play_time": "2023-10-11T04:00:00.000Z", "grade_point": "405.349", "max_golden_ikura_num": 194, "avg_golden_ikura_num": "121.859", "is_clear_by_rate": [99, 80, 49, 20], "is_failure_by_rate": [30, 24, 15, 7], "failure_wave": [3, 9, 18], "shifts_worked": 129}, {"play_time": "2023-10-11T03:30:00.000Z", "grade_point": "370.877", "max_golden_ikura_num": 176, "avg_golden_ikura_num": "117.5", "is_clear_by_rate": [98, 63, 33, 9], "is_failure_by_rate": [56, 46, 35, 16], "failure_wave": [11, 20, 25], "shifts_worked": 154}, {"play_time": "2023-10-11T03:00:00.000Z", "grade_point": "356.788", "max_golden_ikura_num": 157, "avg_golden_ikura_num": "116.593", "is_clear_by_rate": [123, 80, 43, 13], "is_failure_by_rate": [41, 30, 21, 14], "failure_wave": [7, 10, 25], "shifts_worked": 165}, {"play_time": "2023-10-11T02:30:00.000Z", "grade_point": "340.7", "max_golden_ikura_num": 158, "avg_golden_ikura_num": "117.853", "is_clear_by_rate": [109, 74, 36, 16], "is_failure_by_rate": [41, 29, 12, 7], "failure_wave": [5, 11, 25], "shifts_worked": 150}, {"play_time": "2023-10-11T02:00:00.000Z", "grade_point": "342.574", "max_golden_ikura_num": 178, "avg_golden_ikura_num": "119.894", "is_clear_by_rate": [103, 64, 31, 10], "is_failure_by_rate": [32, 21, 12, 7], "failure_wave": [6, 9, 17], "shifts_worked": 136}, {"play_time": "2023-10-11T01:30:00.000Z", "grade_point": "348.596", "max_golden_ikura_num": 161, "avg_golden_ikura_num": "118.907", "is_clear_by_rate": [86, 57, 28, 9], "is_failure_by_rate": [28, 23, 10, 10], "failure_wave": [4, 8, 16], "shifts_worked": 114}, {"play_time": "2023-10-11T01:00:00.000Z", "grade_point": "364.735", "max_golden_ikura_num": 178, "avg_golden_ikura_num": "116.776", "is_clear_by_rate": [75, 48, 22, 14], "is_failure_by_rate": [37, 26, 17, 11], "failure_wave": [6, 16, 15], "shifts_worked": 113}, {"play_time": "2023-10-11T00:30:00.000Z", "grade_point": "362.475", "max_golden_ikura_num": 164, "avg_golden_ikura_num": "117.087", "is_clear_by_rate": [69, 39, 19, 12], "is_failure_by_rate": [32, 25, 16, 12], "failure_wave": [3, 10, 19], "shifts_worked": 101}, {"play_time": "2023-10-11T00:00:00.000Z", "grade_point": "444.934", "max_golden_ikura_num": 160, "avg_golden_ikura_num": "115.382", "is_clear_by_rate": [55, 33, 22, 18], "is_failure_by_rate": [21, 19, 13, 12], "failure_wave": [7, 7, 7], "shifts_worked": 76}, {"play_time": "2023-10-10T23:30:00.000Z", "grade_point": "479.747", "max_golden_ikura_num": 155, "avg_golden_ikura_num": "116.135", "is_clear_by_rate": [52, 34, 23, 17], "is_failure_by_rate": [27, 26, 21, 15], "failure_wave": [9, 4, 14], "shifts_worked": 79}, {"play_time": "2023-10-10T23:00:00.000Z", "grade_point": "456.446", "max_golden_ikura_num": 139, "avg_golden_ikura_num": "114.517", "is_clear_by_rate": [57, 35, 27, 25], "is_failure_by_rate": [24, 20, 17, 15], "failure_wave": [5, 6, 14], "shifts_worked": 83}, {"play_time": "2023-10-10T22:30:00.000Z", "grade_point": "429.57", "max_golden_ikura_num": 169, "avg_golden_ikura_num": "117.871", "is_clear_by_rate": [68, 37, 31, 30], "is_failure_by_rate": [21, 18, 14, 13], "failure_wave": [1, 7, 15], "shifts_worked": 93}, {"play_time": "2023-10-10T22:00:00.000Z", "grade_point": "558.333", "max_golden_ikura_num": 168, "avg_golden_ikura_num": "122.316", "is_clear_by_rate": [77, 61, 51, 47], "is_failure_by_rate": [32, 25, 23, 21], "failure_wave": [7, 5, 20], "shifts_worked": 111}, {"play_time": "2023-10-10T21:30:00.000Z", "grade_point": "644.722", "max_golden_ikura_num": 170, "avg_golden_ikura_num": "128.549", "is_clear_by_rate": [82, 73, 68, 61], "is_failure_by_rate": [26, 24, 21, 15], "failure_wave": [4, 5, 17], "shifts_worked": 108}, {"play_time": "2023-10-10T21:00:00.000Z", "grade_point": "585.214", "max_golden_ikura_num": 184, "avg_golden_ikura_num": "126.437", "is_clear_by_rate": [103, 89, 82, 68], "is_failure_by_rate": [37, 34, 28, 23], "failure_wave": [9, 14, 14], "shifts_worked": 140}, {"play_time": "2023-10-10T20:30:00.000Z", "grade_point": "592.185", "max_golden_ikura_num": 192, "avg_golden_ikura_num": "129.822", "is_clear_by_rate": [107, 99, 92, 68], "is_failure_by_rate": [28, 28, 27, 21], "failure_wave": [5, 8, 15], "shifts_worked": 135}, {"play_time": "2023-10-10T20:00:00.000Z", "grade_point": "552.64", "max_golden_ikura_num": 187, "avg_golden_ikura_num": "130.208", "is_clear_by_rate": [106, 101, 86, 51], "is_failure_by_rate": [19, 18, 17, 8], "failure_wave": [1, 6, 12], "shifts_worked": 125}, {"play_time": "2023-10-10T19:30:00.000Z", "grade_point": "477.429", "max_golden_ikura_num": 175, "avg_golden_ikura_num": "127.206", "is_clear_by_rate": [136, 134, 113, 28], "is_failure_by_rate": [39, 31, 23, 3], "failure_wave": [7, 10, 22], "shifts_worked": 175}, {"play_time": "2023-10-10T19:00:00.000Z", "grade_point": "421.452", "max_golden_ikura_num": 201, "avg_golden_ikura_num": "127.994", "is_clear_by_rate": [171, 160, 126, 1], "is_failure_by_rate": [46, 39, 23, 0], "failure_wave": [8, 8, 30], "shifts_worked": 217}, {"play_time": "2023-10-10T18:30:00.000Z", "grade_point": "356.917", "max_golden_ikura_num": 199, "avg_golden_ikura_num": "124.189", "is_clear_by_rate": [222, 196, 130, 0], "is_failure_by_rate": [44, 31, 16, 0], "failure_wave": [3, 13, 28], "shifts_worked": 266}, {"play_time": "2023-10-10T18:00:00.000Z", "grade_point": "307.641", "max_golden_ikura_num": 191, "avg_golden_ikura_num": "125.667", "is_clear_by_rate": [255, 222, 30, 0], "is_failure_by_rate": [46, 29, 1, 0], "failure_wave": [10, 13, 23], "shifts_worked": 301}, {"play_time": "2023-10-10T17:30:00.000Z", "grade_point": "253.863", "max_golden_ikura_num": 196, "avg_golden_ikura_num": "122.04", "is_clear_by_rate": [350, 289, 0, 0], "is_failure_by_rate": [50, 28, 0, 0], "failure_wave": [14, 16, 20], "shifts_worked": 400}, {"play_time": "2023-10-10T17:00:00.000Z", "grade_point": "185.705", "max_golden_ikura_num": 182, "avg_golden_ikura_num": "120.86", "is_clear_by_rate": [398, 211, 0, 0], "is_failure_by_rate": [46, 14, 0, 0], "failure_wave": [10, 9, 28], "shifts_worked": 447}, {"play_time": "2023-10-10T16:30:00.000Z", "grade_point": "125.632", "max_golden_ikura_num": 181, "avg_golden_ikura_num": "118.633", "is_clear_by_rate": [491, 18, 0, 0], "is_failure_by_rate": [62, 0, 0, 0], "failure_wave": [11, 19, 33], "shifts_worked": 562}, {"play_time": "2023-10-10T16:00:00.000Z", "grade_point": "65.266", "max_golden_ikura_num": 175, "avg_golden_ikura_num": "117.596", "is_clear_by_rate": [575, 0, 0, 0], "is_failure_by_rate": [63, 0, 0, 0], "failure_wave": [14, 21, 28], "shifts_worked": 640}], "waves": [[{"water_level": 2, "event_type": 0, "occurrence": 5383, "is_clear": 4687, "golden_ikura_num": 81}, {"water_level": 0, "event_type": 0, "occurrence": 5372, "is_clear": 5045, "golden_ikura_num": 83}, {"water_level": 1, "event_type": 0, "occurrence": 16038, "is_clear": 14236, "golden_ikura_num": 78}], [{"water_level": 1, "event_type": 1, "occurrence": 792, "is_clear": 654, "golden_ikura_num": 57}, {"water_level": 2, "event_type": 1, "occurrence": 247, "is_clear": 160, "golden_ikura_num": 65}], [{"water_level": 2, "event_type": 2, "occurrence": 280, "is_clear": 273, "golden_ikura_num": 91}, {"water_level": 1, "event_type": 2, "occurrence": 847, "is_clear": 828, "golden_ikura_num": 74}], [{"water_level": 1, "event_type": 3, "occurrence": 852, "is_clear": 842, "golden_ikura_num": 66}, {"water_level": 2, "event_type": 3, "occurrence": 262, "is_clear": 257, "golden_ikura_num": 75}], [{"water_level": 0, "event_type": 4, "occurrence": 205, "is_clear": 204, "golden_ikura_num": 74}, {"water_level": 1, "event_type": 4, "occurrence": 652, "is_clear": 648, "golden_ikura_num": 72}, {"water_level": 2, "event_type": 4, "occurrence": 210, "is_clear": 209, "golden_ikura_num": 87}], [{"water_level": 1, "event_type": 5, "occurrence": 704, "is_clear": 665, "golden_ikura_num": 80}, {"water_level": 2, "event_type": 5, "occurrence": 193, "is_clear": 170, "golden_ikura_num": 91}, {"water_level": 0, "event_type": 5, "occurrence": 205, "is_clear": 198, "golden_ikura_num": 84}], [{"water_level": 0, "event_type": 6, "occurrence": 1101, "is_clear": 1023, "golden_ikura_num": 78}], [{"water_level": 0, "event_type": 7, "occurrence": 1055, "is_clear": 1053, "golden_ikura_num": 72}], [{"water_level": 1, "event_type": 8, "occurrence": 829, "is_clear": 817, "golden_ikura_num": 74}, {"water_level": 2, "event_type": 8, "occurrence": 273, "is_clear": 273, "golden_ikura_num": 92}]]}